<?xml version="1.0" encoding="utf-8" ?>
<form>
    <control name="main_form" entity="Form" script="admin_yBreaker\yBreaker_events_gui\yBreaker_form_spammail" init="on_form_main_init">
        <prop LimitInScreen="true" Left="69" Top="38" Width="270" Height="298" ShadowColor="0,0,0,0" Font="Default" DrawMode="Expand" BackImage="gui\common\form_back\bg_form.png" />
        <event on_open="on_main_form_open" on_close="on_main_form_close" />
        <control name="btn_close" entity="Button" script="" init="">
            <prop NormalImage="gui\common\button\btn_close_out.png" FocusImage="gui\common\button\btn_close_on.png" PushImage="gui\common\button\btn_close_down.png" FocusBlendColor="255,255,255,255" PushBlendColor="255,255,255,255" DisableBlendColor="255,255,255,255" NormalColor="0,0,0,0" FocusColor="0,0,0,0" PushColor="0,0,0,0" DisableColor="0,0,0,0" Left="240" Top="7" Width="20" Height="22" ForeColor="255,255,255,255" BackColor="255,192,192,192" ShadowColor="0,255,255,255" Font="font_main" TabStop="true" AutoSize="true" DrawMode="FitWindow" InSound="MouseOn_20" ClickSound="cancel_5" />
            <event on_click="show_hide_form_spammail" />
        </control>
		<control name="btn_help" entity="Button" script="" init="">
            <prop NormalImage="gui\common\button\btn_help_out.png" FocusImage="gui\common\button\btn_help_on.png" PushImage="gui\common\button\btn_help_down.png" FocusBlendColor="255,255,255,255" PushBlendColor="255,255,255,255" DisableBlendColor="255,255,255,255" NormalColor="0,0,0,0" FocusColor="0,0,0,0" PushColor="0,0,0,0" DisableColor="0,0,0,0" Left="220" Top="7" Width="20" Height="22" ForeColor="255,255,255,255" BackColor="255,192,192,192" ShadowColor="0,255,255,255" Font="font_main" TabStop="true" AutoSize="true" DrawMode="FitWindow" InSound="MouseOn_20" ClickSound="cancel_5" HintText="&lt;font color=&apos;#ffee2e&apos;&gt;Hướng Dẫn:&lt;/font&gt;<br>● Nhập tên người muốn spam thư vào N.Nhận <br>● Nhập tiêu đề thư<br>● Nhập nội dung thư<br>● Nhập số tiền (1x)<br>● Nhập số thư muốn gửi<br>● Bấm &lt;font color=&apos;#46fd15&apos;&gt;Bắt Đầu&lt;/font&gt; để tiến hành spam thư!" />
        </control>
        <control name="lbl_title" entity="Label" script="" init="">
            <prop Align="Center" RefCursor="WIN_HELP" Left="60" Top="6" Width="150" Height="20" ForeColor="255,255,255,255" ShadowColor="0,0,0,0" Text="Nghệ Thuật Gửi Thư" Font="font_title_quaicai" />
        </control>
		 
		 <control name="tab_1_text" entity="Label" script="" init="">
            <prop Align="Right" RefCursor="WIN_HELP" Left="20" Top="51" Width="50" Height="20" ForeColor="255,255,255,255" ShadowColor="0,0,0,0" Text="N.Nhận:" Font="font_main" />
        </control>
		 <control name="tab_1_input" entity="Edit" script="" init="">
            <prop MaxLength="255" TextOffsetX="2" Align="Center" Caret="Default" Left="80" Top="47" Width="160" Height="30" ForeColor="255,255,255,255" BackColor="0,255,255,255" LineColor="0,0,0,0" BlendColor="0,255,255,255" ShadowColor="0,20,0,0" Font="font_text" Cursor="WIN_IBEAM" TabStop="true" DrawMode="ExpandH" Text=""/>
         </control>
		 <control name="tab_1_background" entity="Label" script="" init="">
            <prop RefCursor="WIN_HELP" Left="80" Top="50" Width="180" Height="22" ShadowColor="0,0,0,0" DrawMode="Expand" BackImage="gui\special\battlefield\info.png" />
         </control>
		 
		 <control name="tab_2_text" entity="Label" script="" init="">
            <prop Align="Right" RefCursor="WIN_HELP" Left="20" Top="81" Width="50" Height="20" ForeColor="255,255,255,255" ShadowColor="0,0,0,0" Text="Chủ Đề :" Font="font_main" />
        </control>
		 <control name="tab_2_input" entity="Edit" script="" init="">
            <prop MaxLength="255" TextOffsetX="2" Align="Center" Caret="Default" Left="80" Top="77" Width="160" Height="30" ForeColor="255,255,255,255" BackColor="0,255,255,255" LineColor="0,0,0,0" BlendColor="0,255,255,255" ShadowColor="0,20,0,0" Font="font_text" Cursor="WIN_IBEAM" TabStop="true" DrawMode="ExpandH" Text=""/>
         </control>
		 <control name="tab_2_background" entity="Label" script="" init="">
            <prop RefCursor="WIN_HELP" Left="80" Top="80" Width="180" Height="22" ShadowColor="0,0,0,0" DrawMode="Expand" BackImage="gui\special\battlefield\info.png" />
         </control>
		 
		 <control name="tab_3_text" entity="Label" script="" init="">
            <prop Align="Right" RefCursor="WIN_HELP" Left="20" Top="111" Width="50" Height="20" ForeColor="255,255,255,255" ShadowColor="0,0,0,0" Text="Nội Dung:" Font="font_main" />
        </control>
		
		 <control name="tab_3_input" entity="RichEdit" script="" init="">
            <prop ViewRect="4,4,170,90" MaxLength="256" SelectBackColor="190,190,190,190" Caret="Default" LineHeight="20" ScrollSize="18" HasVScroll="true" Left="80" Top="107" Width="180" Height="86" ForeColor="255,255,255,255" BackColor="0,255,255,255" LineColor="0,255,0,0" ShadowColor="0,20,0,0" Font="font_title_tasktrace" Cursor="WIN_IBEAM" TabStop="true" NoFrame="true" DrawMode="Expand" BackImage="gui\special\battlefield\info.png"/>
            <event on_get_focus="on_txt_content_get_focus" on_enter="on_txt_content_enter" />
            <subor name="VScrollBar">
                <prop Maximum="10" SmallChange="1" LargeChange="5" BackColor="0,224,224,224" LineColor="0,0,0,0" ShadowColor="0,0,0,0" />
                <subor name="DecButton">
                    <prop NormalImage="gui\common\scrollbar\button_1\btn_up_out.png" FocusImage="gui\common\scrollbar\button_1\btn_up_on.png" PushImage="gui\common\scrollbar\button_1\btn_up_down.png" FocusBlendColor="255,255,255,255" PushBlendColor="255,255,255,255" DisableBlendColor="255,255,255,255" NormalColor="0,0,0,0" FocusColor="0,0,0,0" PushColor="0,0,0,0" DisableColor="0,0,0,0" Width="18" Height="15" BackColor="255,192,192,192" ShadowColor="0,0,0,0" />
                </subor>
                <subor name="IncButton">
                    <prop NormalImage="gui\common\scrollbar\button_1\btn_down_out.png" FocusImage="gui\common\scrollbar\button_1\btn_down_on.png" PushImage="gui\common\scrollbar\button_1\btn_down_down.png" FocusBlendColor="255,255,255,255" PushBlendColor="255,255,255,255" DisableBlendColor="255,255,255,255" NormalColor="0,0,0,0" FocusColor="0,0,0,0" PushColor="0,0,0,0" DisableColor="0,0,0,0" Width="18" Height="15" BackColor="255,192,192,192" ShadowColor="0,0,0,0" />
                </subor>
                <subor name="TrackButton">
                    <prop NormalImage="gui\common\scrollbar\button_1\btn_trace_out.png" FocusImage="gui\common\scrollbar\button_1\btn_trace_on.png" PushImage="gui\common\scrollbar\button_1\btn_trace_down.png" FocusBlendColor="255,255,255,255" PushBlendColor="255,255,255,255" DisableBlendColor="255,255,255,255" NormalColor="0,0,0,0" FocusColor="0,0,0,0" PushColor="0,0,0,0" DisableColor="0,0,0,0" Width="18" Height="10" BackColor="255,192,192,192" ShadowColor="0,0,0,0" DrawMode="ExpandH" />
                </subor>
            </subor>
        </control>
		 
		 <control name="tab_4_text" entity="Label" script="" init="">
            <prop Align="Right" RefCursor="WIN_HELP" Left="20" Top="201" Width="50" Height="20" ForeColor="255,255,255,255" ShadowColor="0,0,0,0" Text="Số tiền:" Font="font_main" />
        </control>
		<control name="tab_4_background" entity="Label" script="" init="">
            <prop RefCursor="WIN_HELP" Left="80" Top="200" Width="50" Height="22" ShadowColor="0,0,0,0" DrawMode="Expand" BackImage="gui\special\battlefield\info.png" />
         </control>
		 <control name="tab_4_input" entity="Edit" script="" init="">
            <prop OnlyDigit="true" MaxDigit="99999" MaxLength="4" TextOffsetX="2" Align="Center" Caret="Default" Left="80" Top="197" Width="50" Height="30" ForeColor="255,255,255,255" BackColor="0,255,255,255" LineColor="0,0,0,0" BlendColor="0,255,255,255" ShadowColor="0,20,0,0" Font="font_text" Cursor="WIN_IBEAM" TabStop="true" DrawMode="ExpandH" Text="0"/>
         </control>
		 
		 <control name="tab_6_text" entity="Label" script="" init="">
            <prop Align="Right" RefCursor="WIN_HELP" Left="100" Top="201" Width="50" Height="20" ForeColor="255,255,255,255" ShadowColor="0,0,0,0" Text="xu" Font="font_main" />
        </control>
		 
		 <control name="tab_5_text" entity="Label" script="" init="">
            <prop Align="Right" RefCursor="WIN_HELP" Left="20" Top="231" Width="50" Height="20" ForeColor="255,255,255,255" ShadowColor="0,0,0,0" Text="Số thư:" Font="font_main" />
        </control>
		<control name="tab_5_background" entity="Label" script="" init="">
            <prop RefCursor="WIN_HELP" Left="80" Top="230" Width="50" Height="22" ShadowColor="0,0,0,0" DrawMode="Expand" BackImage="gui\special\battlefield\info.png" />
         </control>
		 <control name="tab_5_input" entity="Edit" script="" init="">
            <prop OnlyDigit="true" MaxDigit="99999" MaxLength="4" TextOffsetX="2" Align="Center" Caret="Default" Left="80" Top="227" Width="50" Height="30" ForeColor="255,255,255,255" BackColor="0,255,255,255" LineColor="0,0,0,0" BlendColor="0,255,255,255" ShadowColor="0,20,0,0" Font="font_text" Cursor="WIN_IBEAM" TabStop="true" DrawMode="ExpandH" Text="0"/>
         </control>
		
		<control name="btn_control" entity="Button" script="" init="">
			<prop NormalImage="gui\common\button\btn_normal_out.png" FocusImage="gui\common\button\btn_normal_on.png" PushImage="gui\common\button\btn_normal_down.png" DisableImage="gui\common\button\btn_normal_forbid.png" FocusBlendColor="255,255,255,255" PushBlendColor="255,255,255,255" DisableBlendColor="255,255,255,255" NormalColor="0,0,0,0" FocusColor="0,0,0,0" PushColor="0,0,0,0" DisableColor="0,0,0,0" Left="91" Top="260" Width="87" Height="30" ForeColor="255,255,255,255" BackColor="255,192,192,192" ShadowColor="0,0,0,0" Text="Bắt Đầu"  Font="font_main" TabStop="true" AutoSize="true" InSound="MouseOn_20" ClickSound="ok_7" />
			<event on_click="DoSendMail" />
		</control>
    </control>
</form>
